microschc/__init__.py
microschc/compat.py
microschc/rfc8724.py
microschc/rfc8724extras.py
microschc/actions/__init__.py
microschc/actions/compression.py
microschc/binary/__init__.py
microschc/binary/buffer.py
microschc/compressor/__init__.py
microschc/compressor/compressor.py
microschc/crypto/__init__.py
microschc/crypto/crc.py
microschc/decompressor/__init__.py
microschc/decompressor/decompressor.py
microschc/extras/__init__.py
microschc/extras/io/__init__.py
microschc/extras/io/pcapng/__init__.py
microschc/extras/io/pcapng/pcapng.py
microschc/manager/__init__.py
microschc/manager/manager.py
microschc/matching/__init__.py
microschc/matching/operators.py
microschc/parser/__init__.py
microschc/parser/parser.py
microschc/protocol/__init__.py
microschc/protocol/coap.py
microschc/protocol/compute.py
microschc/protocol/gtp.py
microschc/protocol/gtp_v1.py
microschc/protocol/gtp_v2.py
microschc/protocol/ipv4.py
microschc/protocol/ipv6.py
microschc/protocol/registry.py
microschc/protocol/sctp.py
microschc/protocol/udp.py
microschc/ruler/__init__.py
microschc/ruler/ruler.py
microschc/tools/__init__.py
microschc/tools/cda.py
microschc/tools/matchingoperator.py
microschc/tools/mo.py
microschc/tools/targetvalue.py
microschc-0.21.0.dist-info/METADATA
microschc-0.21.0.dist-info/WHEEL
microschc-0.21.0.dist-info/licenses/LICENSE
microschc-0.21.0.dist-info/RECORD
