Metadata-Version: 2.4
Name: microschc
Version: 0.21.0
Summary: A Python implementation of the Static Context Header Compression (SCHC) protocol
Project-URL: Homepage, https://github.com/quentinlampin/microschc/
Project-URL: Bug Tracker, https://github.com/quentinlampin/microschc/issues
Author-email: Quentin Lampin <quentin.lampin@orange.com>
Maintainer-email: Quentin Lampin <quentin.lampin@orange.com>
License: MIT
License-File: LICENSE
Keywords: compression,iot,lpwan,schc
Classifier: Development Status :: 3 - Alpha
Classifier: Intended Audience :: Developers
Classifier: License :: OSI Approved :: MIT License
Classifier: Operating System :: OS Independent
Classifier: Programming Language :: Python :: 3
Classifier: Programming Language :: Python :: 3.8
Classifier: Programming Language :: Python :: 3.9
Classifier: Programming Language :: Python :: 3.10
Classifier: Programming Language :: Python :: 3.11
Classifier: Topic :: Communications
Classifier: Topic :: Software Development :: Libraries :: Python Modules
Requires-Python: >=3.8
Requires-Dist: backports-strenum; python_version < '3.11'
Requires-Dist: typing-extensions>=4.0.0
Provides-Extra: extras
Requires-Dist: python-pcapng; extra == 'extras'
